{
    "pageNumber": 24,
    "data": [
        {
            "id": "123179474",
            "title": "[1508455778] Slicing Smoked Salmon - Gordon Ramsay",
            "date_created": "1264688576",
            "loginId": "1758991",
            "tags": "",
            "description": "Gordon Ramsay learns how to hand slice smoked salmon.",
            "asset": {
                "type": "youtube",
                "thumbnailUrl": "https:\/\/i.ytimg.com\/vi\/UmkBn25IcL0\/sddefault.jpg",
                "uploadDate": 1264688576,
                "videoId": "UmkBn25IcL0",
                "title": "Slicing Smoked Salmon - Gordon Ramsay",
                "description": "Gordon Ramsay learns how to hand slice smoked salmon.",
                "author": "Gordon Ramsay",
                "mediaDuration": 146,
                "prettyDuration": "00:02:26",
                "views": "418275"
            },
            "parentId": "123179143",
            "url": "\/food-network\/slicing-smoked-salmon-gordon-ramsay\/123179143-123179474"
        },
        {
            "id": "123179473",
            "title": "[1508455778] Salmon slicing world record - Gordon Ramsay",
            "date_created": "1264688596",
            "loginId": "1758991",
            "tags": "",
            "description": "Gordon Ramsay challenges an expert to the world record for hand slicing smoked salmon for Cookalong Live show.\n\nSubscribe Here: http:\/\/www.youtube.com\/subscription_center?src_vid=frUO65rWSmU&add_user=gordonramsay&feature=iv&annotation_id=annotation_508980",
            "asset": {
                "type": "youtube",
                "thumbnailUrl": "https:\/\/i.ytimg.com\/vi\/bGJ6o09q0fQ\/sddefault.jpg",
                "uploadDate": 1264688596,
                "videoId": "bGJ6o09q0fQ",
                "title": "Salmon slicing world record - Gordon Ramsay",
                "description": "Gordon Ramsay challenges an expert to the world record for hand slicing smoked salmon for Cookalong Live show.\n\nSubscribe Here: http:\/\/www.youtube.com\/subscription_center?src_vid=frUO65rWSmU&add_user=gordonramsay&feature=iv&annotation_id=annotation_508980",
                "author": "Gordon Ramsay",
                "mediaDuration": 137,
                "prettyDuration": "00:02:17",
                "views": "7724661"
            },
            "parentId": "123179143",
            "url": "\/food-network\/salmon-slicing-world-record-gordon-ramsay\/123179143-123179473"
        },
        {
            "id": "123179472",
            "title": "[1508455778] Tiramisu (Part 1) - Gordon Ramsay",
            "date_created": "1264688802",
            "loginId": "1758991",
            "tags": "",
            "description": "Gordon Ramsay shows Amanda Holden how to make his quick Tiramisu on the Cookalong Live show.",
            "asset": {
                "type": "youtube",
                "thumbnailUrl": "https:\/\/i.ytimg.com\/vi\/zb__YSEshqk\/hqdefault.jpg",
                "uploadDate": 1264688802,
                "videoId": "zb__YSEshqk",
                "title": "Tiramisu (Part 1) - Gordon Ramsay",
                "description": "Gordon Ramsay shows Amanda Holden how to make his quick Tiramisu on the Cookalong Live show.",
                "author": "Gordon Ramsay",
                "mediaDuration": 74,
                "prettyDuration": "00:01:14",
                "views": "93587"
            },
            "parentId": "123179143",
            "url": "\/food-network\/tiramisu-part-1-gordon-ramsay\/123179143-123179472"
        },
        {
            "id": "123179471",
            "title": "[1508455778] Tiramisu - (Part 2) - Gordon Ramsay",
            "date_created": "1264688858",
            "loginId": "1758991",
            "tags": "",
            "description": "Gordon Ramsay shows Amanda holden how to finish off his quick tiramisu on the Cookalong Live show.",
            "asset": {
                "type": "youtube",
                "thumbnailUrl": "https:\/\/i.ytimg.com\/vi\/nkN3xLxw4K8\/hqdefault.jpg",
                "uploadDate": 1264688858,
                "videoId": "nkN3xLxw4K8",
                "title": "Tiramisu - (Part 2) - Gordon Ramsay",
                "description": "Gordon Ramsay shows Amanda holden how to finish off his quick tiramisu on the Cookalong Live show.",
                "author": "Gordon Ramsay",
                "mediaDuration": 72,
                "prettyDuration": "00:01:12",
                "views": "61413"
            },
            "parentId": "123179143",
            "url": "\/food-network\/tiramisu-part-2-gordon-ramsay\/123179143-123179471"
        },
        {
            "id": "123179470",
            "title": "[1508455778] Learning Turkish Cuisine - Gordon Ramsay",
            "date_created": "1267173164",
            "loginId": "1758991",
            "tags": "",
            "description": "Gordon Ramsay goes back to the floor to learn how to make traditional Turkish food.",
            "asset": {
                "type": "youtube",
                "thumbnailUrl": "https:\/\/i.ytimg.com\/vi\/T9H7jFYvRGQ\/hqdefault.jpg",
                "uploadDate": 1267173164,
                "videoId": "T9H7jFYvRGQ",
                "title": "Learning Turkish Cuisine - Gordon Ramsay",
                "description": "Gordon Ramsay goes back to the floor to learn how to make traditional Turkish food.",
                "author": "Gordon Ramsay",
                "mediaDuration": 162,
                "prettyDuration": "00:02:42",
                "views": "38427"
            },
            "parentId": "123179143",
            "url": "\/food-network\/learning-turkish-cuisine-gordon-ramsay\/123179143-123179470"
        },
        {
            "id": "123179469",
            "title": "[1508455778] Quick Tiramisu - Gordon Ramsay",
            "date_created": "1267172862",
            "loginId": "1758991",
            "tags": "",
            "description": "A very quick recipe for a quick Tiramisu from Gordon's Cookalong Live show. You might need to watch the video a couple of times. Subscribe for weekly videos.",
            "asset": {
                "type": "youtube",
                "thumbnailUrl": "https:\/\/i.ytimg.com\/vi\/tz5IrjY0sr4\/sddefault.jpg",
                "uploadDate": 1267172862,
                "videoId": "tz5IrjY0sr4",
                "title": "Quick Tiramisu - Gordon Ramsay",
                "description": "A very quick recipe for a quick Tiramisu from Gordon's Cookalong Live show. You might need to watch the video a couple of times. Subscribe for weekly videos.",
                "author": "Gordon Ramsay",
                "mediaDuration": 27,
                "prettyDuration": "00:00:27",
                "views": "1293230"
            },
            "parentId": "123179143",
            "url": "\/food-network\/quick-tiramisu-gordon-ramsay\/123179143-123179469"
        },
        {
            "id": "123179468",
            "title": "[1508455778] Gordon gives Amanda Holden an Exploding Pan - Gordon Ramsay",
            "date_created": "1267173205",
            "loginId": "1758991",
            "tags": "",
            "description": "Gordon Ramsay talks to Amanda Holden about running the marathon and Simon Cowell on Cookalong Live and cooks spicy pasta.",
            "asset": {
                "type": "youtube",
                "thumbnailUrl": "https:\/\/i.ytimg.com\/vi\/ZmXPqVtziss\/sddefault.jpg",
                "uploadDate": 1267173205,
                "videoId": "ZmXPqVtziss",
                "title": "Gordon gives Amanda Holden an Exploding Pan - Gordon Ramsay",
                "description": "Gordon Ramsay talks to Amanda Holden about running the marathon and Simon Cowell on Cookalong Live and cooks spicy pasta.",
                "author": "Gordon Ramsay",
                "mediaDuration": 145,
                "prettyDuration": "00:02:25",
                "views": "190842"
            },
            "parentId": "123179143",
            "url": "\/food-network\/gordon-gives-amanda-holden-an-exploding-pan-gordon-ramsay\/123179143-123179468"
        },
        {
            "id": "123179467",
            "title": "[1508455778] Assembling Lasagne with Jonny Vegas - Gordon Ramsay",
            "date_created": "1267173251",
            "loginId": "1758991",
            "tags": "",
            "description": "Gordon Ramsay shows Jonny Vegas how to assemble a classic lasagne. Funny cilp from Cookalong Live.",
            "asset": {
                "type": "youtube",
                "thumbnailUrl": "https:\/\/i.ytimg.com\/vi\/JaNOM1QQZVk\/hqdefault.jpg",
                "uploadDate": 1267173251,
                "videoId": "JaNOM1QQZVk",
                "title": "Assembling Lasagne with Jonny Vegas - Gordon Ramsay",
                "description": "Gordon Ramsay shows Jonny Vegas how to assemble a classic lasagne. Funny cilp from Cookalong Live.",
                "author": "Gordon Ramsay",
                "mediaDuration": 126,
                "prettyDuration": "00:02:06",
                "views": "79423"
            },
            "parentId": "123179143",
            "url": "\/food-network\/assembling-lasagne-with-jonny-vegas-gordon-ramsay\/123179143-123179467"
        },
        {
            "id": "123179466",
            "title": "[1508455778] Cooking Pantomime with Jonny Vegas - Gordon Ramsay",
            "date_created": "1267173018",
            "loginId": "1758991",
            "tags": "",
            "description": "Gordon Ramsay shows Jonny Vegas how to prepare the meat sauce for a classic lasagne. Funny clip from Cookalong Live.",
            "asset": {
                "type": "youtube",
                "thumbnailUrl": "https:\/\/i.ytimg.com\/vi\/CGtOyHNf4B8\/hqdefault.jpg",
                "uploadDate": 1267173018,
                "videoId": "CGtOyHNf4B8",
                "title": "Cooking Pantomime with Jonny Vegas - Gordon Ramsay",
                "description": "Gordon Ramsay shows Jonny Vegas how to prepare the meat sauce for a classic lasagne. Funny clip from Cookalong Live.",
                "author": "Gordon Ramsay",
                "mediaDuration": 124,
                "prettyDuration": "00:02:04",
                "views": "13774"
            },
            "parentId": "123179143",
            "url": "\/food-network\/cooking-pantomime-with-jonny-vegas-gordon-ramsay\/123179143-123179466"
        },
        {
            "id": "123179465",
            "title": "[1508455778] Dragons Den Judges sample Lasagne - Gordon Ramsay",
            "date_created": "1267173249",
            "loginId": "1758991",
            "tags": "",
            "description": "Gordon Ramsay and Jonny Vegas serve lasagne to the Dragons Den judges and Jonny's dad. Plus Jonny has swapped his desserts with Gordon's to make his look better. From Cookalong Live credit crunch special.",
            "asset": {
                "type": "youtube",
                "thumbnailUrl": "https:\/\/i.ytimg.com\/vi\/hujf4RHSEmA\/sddefault.jpg",
                "uploadDate": 1267173249,
                "videoId": "hujf4RHSEmA",
                "title": "Dragons Den Judges sample Lasagne - Gordon Ramsay",
                "description": "Gordon Ramsay and Jonny Vegas serve lasagne to the Dragons Den judges and Jonny's dad. Plus Jonny has swapped his desserts with Gordon's to make his look better. From Cookalong Live credit crunch special.",
                "author": "Gordon Ramsay",
                "mediaDuration": 86,
                "prettyDuration": "00:01:26",
                "views": "120205"
            },
            "parentId": "123179143",
            "url": "\/food-network\/dragons-den-judges-sample-lasagne-gordon-ramsay\/123179143-123179465"
        },
        {
            "id": "123179464",
            "title": "[1508455778] Tricking Raymond Blanc - Gordon Ramsay",
            "date_created": "1267173384",
            "loginId": "1758991",
            "tags": "",
            "description": "Gordon Ramsay wears a disguise to trick Raymond Blanc into signing him a book and taking a picture with him.",
            "asset": {
                "type": "youtube",
                "thumbnailUrl": "https:\/\/i.ytimg.com\/vi\/KROVbR3MF4E\/sddefault.jpg",
                "uploadDate": 1267173384,
                "videoId": "KROVbR3MF4E",
                "title": "Tricking Raymond Blanc - Gordon Ramsay",
                "description": "Gordon Ramsay wears a disguise to trick Raymond Blanc into signing him a book and taking a picture with him.",
                "author": "Gordon Ramsay",
                "mediaDuration": 90,
                "prettyDuration": "00:01:30",
                "views": "1953882"
            },
            "parentId": "123179143",
            "url": "\/food-network\/tricking-raymond-blanc-gordon-ramsay\/123179143-123179464"
        },
        {
            "id": "123179463",
            "title": "[1508455778] Amanda Holden does the Splits - Gordon Ramsay",
            "date_created": "1267172818",
            "loginId": "1758991",
            "tags": "",
            "description": "Amanda Holden does the splits for Gordon Ramsay on the Cookalong Live show.",
            "asset": {
                "type": "youtube",
                "thumbnailUrl": "https:\/\/i.ytimg.com\/vi\/gtyuzwLpuCw\/sddefault.jpg",
                "uploadDate": 1267172818,
                "videoId": "gtyuzwLpuCw",
                "title": "Amanda Holden does the Splits - Gordon Ramsay",
                "description": "Amanda Holden does the splits for Gordon Ramsay on the Cookalong Live show.",
                "author": "Gordon Ramsay",
                "mediaDuration": 44,
                "prettyDuration": "00:00:44",
                "views": "361623"
            },
            "parentId": "123179143",
            "url": "\/food-network\/amanda-holden-does-the-splits-gordon-ramsay\/123179143-123179463"
        },
        {
            "id": "123179462",
            "title": "[1508455778] Bombay Oranges with Herb Sugar & Pomegranates - Gordon Ramsay",
            "date_created": "1267173242",
            "loginId": "1758991",
            "tags": "",
            "description": "Gordon Ramsay shows Alan Carr how to make his dessert: Bombay Oranges. From the Indian special Cookalong Live Show.",
            "asset": {
                "type": "youtube",
                "thumbnailUrl": "https:\/\/i.ytimg.com\/vi\/4rez_nap27w\/hqdefault.jpg",
                "uploadDate": 1267173242,
                "videoId": "4rez_nap27w",
                "title": "Bombay Oranges with Herb Sugar & Pomegranates - Gordon Ramsay",
                "description": "Gordon Ramsay shows Alan Carr how to make his dessert: Bombay Oranges. From the Indian special Cookalong Live Show.",
                "author": "Gordon Ramsay",
                "mediaDuration": 170,
                "prettyDuration": "00:02:50",
                "views": "61768"
            },
            "parentId": "123179143",
            "url": "\/food-network\/bombay-oranges-with-herb-sugar-pomegranates-gordon-ramsay\/123179143-123179462"
        },
        {
            "id": "123179461",
            "title": "[1508455778] Recipe challenge with Hardeep Singh Kohli - Gordon Ramsay",
            "date_created": "1267173588",
            "loginId": "1758991",
            "tags": "",
            "description": "Hardeep Singh Kohli challenges Gordon Ramsay to cook the best Cock-a-leekie soup. From Cookalong Live. Plus Hardeep shows Gordon how to tie a turban.",
            "asset": {
                "type": "youtube",
                "thumbnailUrl": "https:\/\/i.ytimg.com\/vi\/w-Y5q3b_GZ4\/hqdefault.jpg",
                "uploadDate": 1267173588,
                "videoId": "w-Y5q3b_GZ4",
                "title": "Recipe challenge with Hardeep Singh Kohli - Gordon Ramsay",
                "description": "Hardeep Singh Kohli challenges Gordon Ramsay to cook the best Cock-a-leekie soup. From Cookalong Live. Plus Hardeep shows Gordon how to tie a turban.",
                "author": "Gordon Ramsay",
                "mediaDuration": 181,
                "prettyDuration": "00:03:01",
                "views": "78085"
            },
            "parentId": "123179143",
            "url": "\/food-network\/recipe-challenge-with-hardeep-singh-kohli-gordon-ramsay\/123179143-123179461"
        },
        {
            "id": "123179460",
            "title": "[1508455778] Chicken Tikka Masala - Gordon Ramsay",
            "date_created": "1267172860",
            "loginId": "1758991",
            "tags": "",
            "description": "Gordon Ramsay's recipe for a classic Tikka Masala sauce.",
            "asset": {
                "type": "youtube",
                "thumbnailUrl": "https:\/\/i.ytimg.com\/vi\/y-VjBxMufhw\/sddefault.jpg",
                "uploadDate": 1267172860,
                "videoId": "y-VjBxMufhw",
                "title": "Chicken Tikka Masala - Gordon Ramsay",
                "description": "Gordon Ramsay's recipe for a classic Tikka Masala sauce.",
                "author": "Gordon Ramsay",
                "mediaDuration": 41,
                "prettyDuration": "00:00:41",
                "views": "1783046"
            },
            "parentId": "123179143",
            "url": "\/food-network\/chicken-tikka-masala-gordon-ramsay\/123179143-123179460"
        },
        {
            "id": "123179459",
            "title": "[1508455778] Finishing crab pasta with Amanda Holden - Gordon Ramsay",
            "date_created": "1267173101",
            "loginId": "1758991",
            "tags": "",
            "description": "Gordon Ramsay shows Amanda Holden how to finish her crab pasta dish on the Cookalong Live show.",
            "asset": {
                "type": "youtube",
                "thumbnailUrl": "https:\/\/i.ytimg.com\/vi\/-l74GzxwzLw\/hqdefault.jpg",
                "uploadDate": 1267173101,
                "videoId": "-l74GzxwzLw",
                "title": "Finishing crab pasta with Amanda Holden - Gordon Ramsay",
                "description": "Gordon Ramsay shows Amanda Holden how to finish her crab pasta dish on the Cookalong Live show.",
                "author": "Gordon Ramsay",
                "mediaDuration": 167,
                "prettyDuration": "00:02:47",
                "views": "59753"
            },
            "parentId": "123179143",
            "url": "\/food-network\/finishing-crab-pasta-with-amanda-holden-gordon-ramsay\/123179143-123179459"
        },
        {
            "id": "123179458",
            "title": "[1508455778] Crab pasta with Amanda Holden - Gordon Ramsay",
            "date_created": "1267174133",
            "loginId": "1758991",
            "tags": "",
            "description": "Gordon Ramsay finishes off crab pasta with Amanda Holden on the Cookalong Live show.",
            "asset": {
                "type": "youtube",
                "thumbnailUrl": "https:\/\/i.ytimg.com\/vi\/eDSE2_v65Mc\/hqdefault.jpg",
                "uploadDate": 1267174133,
                "videoId": "eDSE2_v65Mc",
                "title": "Crab pasta with Amanda Holden - Gordon Ramsay",
                "description": "Gordon Ramsay finishes off crab pasta with Amanda Holden on the Cookalong Live show.",
                "author": "Gordon Ramsay",
                "mediaDuration": 59,
                "prettyDuration": "00:00:59",
                "views": "12234"
            },
            "parentId": "123179143",
            "url": "\/food-network\/crab-pasta-with-amanda-holden-gordon-ramsay\/123179143-123179458"
        },
        {
            "id": "123179457",
            "title": "[1508455778] Learning Turkish Cuisine - Gordon Ramsay",
            "date_created": "1267174352",
            "loginId": "1758991",
            "tags": "",
            "description": "Gordon Ramsay goes back to the floor to learn how to make traditional Turkish food.",
            "asset": {
                "type": "youtube",
                "thumbnailUrl": "https:\/\/i.ytimg.com\/vi\/VeEVdw5EGyA\/sddefault.jpg",
                "uploadDate": 1267174352,
                "videoId": "VeEVdw5EGyA",
                "title": "Learning Turkish Cuisine - Gordon Ramsay",
                "description": "Gordon Ramsay goes back to the floor to learn how to make traditional Turkish food.",
                "author": "Gordon Ramsay",
                "mediaDuration": 165,
                "prettyDuration": "00:02:45",
                "views": "895908"
            },
            "parentId": "123179143",
            "url": "\/food-network\/learning-turkish-cuisine-gordon-ramsay\/123179143-123179457"
        },
        {
            "id": "123179456",
            "title": "[1508455778] 'I'm a Chef and You're a Cook' - Gordon Ramsay vs. Alan Carr",
            "date_created": "1270116764",
            "loginId": "1758991",
            "tags": "",
            "description": "Alan Carr challenges Gordon Ramsay to cook a better thai green curry recipe than him. From Cookalong Live.",
            "asset": {
                "type": "youtube",
                "thumbnailUrl": "https:\/\/i.ytimg.com\/vi\/op-iNUoxc6Y\/hqdefault.jpg",
                "uploadDate": 1270116764,
                "videoId": "op-iNUoxc6Y",
                "title": "'I'm a Chef and You're a Cook' - Gordon Ramsay vs. Alan Carr",
                "description": "Alan Carr challenges Gordon Ramsay to cook a better thai green curry recipe than him. From Cookalong Live.",
                "author": "Gordon Ramsay",
                "mediaDuration": 166,
                "prettyDuration": "00:02:46",
                "views": "546433"
            },
            "parentId": "123179143",
            "url": "\/food-network\/i-m-a-chef-and-you-re-a-cook-gordon-ramsay-vs-alan-carr\/123179143-123179456"
        },
        {
            "id": "123179455",
            "title": "[1508455778] Not Happy with Results of Alan Carr Challenge - Gordon Ramsay",
            "date_created": "1270116591",
            "loginId": "1758991",
            "tags": "",
            "description": "Gordon Ramsay and Alan Carr go head to head in a recipe challenge to cook the best Thai Green Curry. From Cookalong Live.",
            "asset": {
                "type": "youtube",
                "thumbnailUrl": "https:\/\/i.ytimg.com\/vi\/Zb0hagZ0N54\/hqdefault.jpg",
                "uploadDate": 1270116591,
                "videoId": "Zb0hagZ0N54",
                "title": "Not Happy with Results of Alan Carr Challenge - Gordon Ramsay",
                "description": "Gordon Ramsay and Alan Carr go head to head in a recipe challenge to cook the best Thai Green Curry. From Cookalong Live.",
                "author": "Gordon Ramsay",
                "mediaDuration": 63,
                "prettyDuration": "00:01:03",
                "views": "263288"
            },
            "parentId": "123179143",
            "url": "\/food-network\/not-happy-with-results-of-alan-carr-challenge-gordon-ramsay\/123179143-123179455"
        }
    ]
}