{
    "title": "[1508428454] How to Poach and Flavour Salmon - Gordon Ramsay",
    "description": "From Christmas with Gordon (2010). Poached salmon is perfect is Gordon's festive Nicoise salad, for parties, lunches or any occasion where you fancy something light. \n\nSubscribe for weekly cooking videos. \n\nIf you liked this clip check out the rest of Gordon's channels:\n\nhttp:\/\/www.youtube.com\/gordonramsay\nhttp:\/\/www.youtube.com\/kitchennightmares\nhttp:\/\/www.youtube.com\/thefword",
    "referenceId": "3Vvx0cQf718",
    "date_created": "1418320817",
    "date_modified": "1508373258",
    "tags": "",
    "sourceId": "4",
    "status": "approved",
    "visibility": "1",
    "VV_VI": null,
    "engagement_score": null,
    "conversion_score": null,
    "CVV_VI": null,
    "concept": null,
    "homepage_gallery": null,
    "living": null,
    "id": "123179130",
    "loginId": "1758991",
    "entityType": "1",
    "titleTextEncoded": "How-to-Poach-and-Flavour-Salmon-Gordon-Ramsay",
    "category": "",
    "tvp_profiles": [
        "25",
        "18",
        "11"
    ],
    "tvp_profiles_manual": "",
    "tvp_profiles_maxscore": 498.97678,
    "VIDEO_LENGTH": "SHORT",
    "duration": 103,
    "settings": "",
    "asset": {
        "type": "youtube",
        "thumbnailUrl": "https:\/\/i.ytimg.com\/vi\/3Vvx0cQf718\/maxresdefault.jpg",
        "uploadDate": 1418320817,
        "videoId": "3Vvx0cQf718",
        "title": "How to Poach and Flavour Salmon - Gordon Ramsay",
        "description": "From Christmas with Gordon (2010). Poached salmon is perfect is Gordon's festive Nicoise salad, for parties, lunches or any occasion where you fancy something light. \n\nSubscribe for weekly cooking videos. \n\nIf you liked this clip check out the rest of Gordon's channels:\n\nhttp:\/\/www.youtube.com\/gordonramsay\nhttp:\/\/www.youtube.com\/kitchennightmares\nhttp:\/\/www.youtube.com\/thefword",
        "author": "Gordon Ramsay",
        "mediaDuration": 103,
        "prettyDuration": "00:01:43",
        "views": "347441"
    },
    "transcripts": "",
    "metrics_statistics": "",
    "uploader": ""
}