{
    "title": "[1508443598] StoreSmith by Wonder Hanger 5pack",
    "description": "For More Info or to Buy Now: http:\/\/www.hsn.com\/products\/seo\/8170629?rdr=1&sourceid=youtube&cm_mmc=Social-_-Youtube-_-ProductVideo-_-088408\r\nStoreSmith by Wonder Hanger 5pack \nYou could always use a little more space in your closet. With this cascading hanger, you can hang more clothes in the same space. Each of the slots accommodates...\r\nPrices shown on the previously recorded video may not represent the current price.  View hsn.com to view the current selling price. HSN Item #088408",
    "referenceId": "g6yzDp3aDxw",
    "date_created": "1507989202",
    "date_modified": "1508372601",
    "tags": "",
    "sourceId": "4",
    "status": "approved",
    "visibility": "1",
    "VV_VI": null,
    "engagement_score": null,
    "conversion_score": null,
    "CVV_VI": null,
    "concept": null,
    "homepage_gallery": null,
    "living": null,
    "id": "123178741",
    "loginId": "1758991",
    "entityType": "1",
    "titleTextEncoded": "StoreSmith-by-Wonder-Hanger-5pack",
    "category": "",
    "tvp_profiles": [
        "9"
    ],
    "tvp_profiles_manual": "",
    "tvp_profiles_maxscore": 2240.623,
    "VIDEO_LENGTH": "LONG",
    "duration": 619,
    "settings": "",
    "asset": {
        "type": "youtube",
        "thumbnailUrl": "https:\/\/i.ytimg.com\/vi\/g6yzDp3aDxw\/sddefault.jpg",
        "uploadDate": 1507989202,
        "videoId": "g6yzDp3aDxw",
        "title": "StoreSmith by Wonder Hanger 5pack",
        "description": "For More Info or to Buy Now: http:\/\/www.hsn.com\/products\/seo\/8170629?rdr=1&sourceid=youtube&cm_mmc=Social-_-Youtube-_-ProductVideo-_-088408\r\nStoreSmith by Wonder Hanger 5pack \nYou could always use a little more space in your closet. With this cascading hanger, you can hang more clothes in the same space. Each of the slots accommodates...\r\nPrices shown on the previously recorded video may not represent the current price.  View hsn.com to view the current selling price. HSN Item #088408",
        "author": "HSNtv",
        "mediaDuration": 619,
        "prettyDuration": "00:10:19",
        "views": "25"
    },
    "transcripts": "",
    "metrics_statistics": "",
    "uploader": ""
}