{
    "title": "[1508440185] 14K White Gold 8.63ctw Pink Kunzite and Zircon Ring",
    "description": "For More Info or to Buy Now: http:\/\/www.hsn.com\/products\/seo\/8519899?rdr=1&sourceid=youtube&cm_mmc=Social-_-Youtube-_-ProductVideo-_-578255\r\n14K White Gold 8.63ctw Pink Kunzite and Zircon Ring \nDon't reserve those intense looks for your crush alone. This ring ignites the kind of subtle fire that's sure to spark more interest. A pink...\r\nPrices shown on the previously recorded video may not represent the current price.  View hsn.com to view the current selling price. HSN Item #578255",
    "referenceId": "3VRTkoWDaXA",
    "date_created": "1508116636",
    "date_modified": "1508372597",
    "tags": "",
    "sourceId": "4",
    "status": "approved",
    "visibility": "1",
    "VV_VI": null,
    "engagement_score": null,
    "conversion_score": null,
    "CVV_VI": null,
    "concept": null,
    "homepage_gallery": null,
    "living": null,
    "id": "123178612",
    "loginId": "1758991",
    "entityType": "1",
    "titleTextEncoded": "14K-White-Gold-8-63ctw-Pink-Kunzite-and-Zircon-Ring",
    "category": "",
    "tvp_profiles": null,
    "tvp_profiles_manual": "",
    "tvp_profiles_maxscore": 0,
    "VIDEO_LENGTH": "LONG",
    "duration": 247,
    "settings": "",
    "asset": {
        "type": "youtube",
        "thumbnailUrl": "https:\/\/i.ytimg.com\/vi\/3VRTkoWDaXA\/sddefault.jpg",
        "uploadDate": 1508116636,
        "videoId": "3VRTkoWDaXA",
        "title": "14K White Gold 8.63ctw Pink Kunzite and Zircon Ring",
        "description": "For More Info or to Buy Now: http:\/\/www.hsn.com\/products\/seo\/8519899?rdr=1&sourceid=youtube&cm_mmc=Social-_-Youtube-_-ProductVideo-_-578255\r\n14K White Gold 8.63ctw Pink Kunzite and Zircon Ring \nDon't reserve those intense looks for your crush alone. This ring ignites the kind of subtle fire that's sure to spark more interest. A pink...\r\nPrices shown on the previously recorded video may not represent the current price.  View hsn.com to view the current selling price. HSN Item #578255",
        "author": "HSNtv",
        "mediaDuration": 247,
        "prettyDuration": "00:04:07",
        "views": "15"
    },
    "transcripts": "",
    "metrics_statistics": "",
    "uploader": ""
}