{
    "title": "[1508428454] Nervous Chef Desperate to 'Amaze' Gordon Ramsay | Culinary Genius",
    "description": "The trainee chef can't get his words out. \n\nCulinary Genius will see nine amateur cooks head into a wrestling ring-style studio to do culinary battle.\n\nSubscribe for weekly cooking videos. \n\nIf you liked this clip check out the rest of Gordon's channels:\n\nhttp:\/\/www.youtube.com\/gordonramsay\nhttp:\/\/www.youtube.com\/kitchennightmares\nhttp:\/\/www.youtube.com\/thefword",
    "referenceId": "cC1qpBbuNyo",
    "date_created": "1493398804",
    "date_modified": "1508373253",
    "tags": "",
    "sourceId": "4",
    "status": "approved",
    "visibility": "1",
    "VV_VI": null,
    "engagement_score": null,
    "conversion_score": null,
    "CVV_VI": null,
    "concept": null,
    "homepage_gallery": null,
    "living": null,
    "id": "123178970",
    "loginId": "1758991",
    "entityType": "1",
    "titleTextEncoded": "Nervous-Chef-Desperate-to-Amaze-Gordon-Ramsay-Culinary-Genius",
    "category": "",
    "tvp_profiles": [
        "14",
        "18",
        "25"
    ],
    "tvp_profiles_manual": "",
    "tvp_profiles_maxscore": 423.44925,
    "VIDEO_LENGTH": "SHORT",
    "duration": 95,
    "settings": "",
    "asset": {
        "type": "youtube",
        "thumbnailUrl": "https:\/\/i.ytimg.com\/vi\/cC1qpBbuNyo\/maxresdefault.jpg",
        "uploadDate": 1493398804,
        "videoId": "cC1qpBbuNyo",
        "title": "Nervous Chef Desperate to 'Amaze' Gordon Ramsay | Culinary Genius",
        "description": "The trainee chef can't get his words out. \n\nCulinary Genius will see nine amateur cooks head into a wrestling ring-style studio to do culinary battle.\n\nSubscribe for weekly cooking videos. \n\nIf you liked this clip check out the rest of Gordon's channels:\n\nhttp:\/\/www.youtube.com\/gordonramsay\nhttp:\/\/www.youtube.com\/kitchennightmares\nhttp:\/\/www.youtube.com\/thefword",
        "author": "Gordon Ramsay",
        "mediaDuration": 95,
        "prettyDuration": "00:01:35",
        "views": "434032"
    },
    "transcripts": "",
    "metrics_statistics": "",
    "uploader": ""
}