{
    "title": "[1508429236] Handy Heater PlugIn Personal Heater w\/Remote Control",
    "description": "For More Info or to Buy Now: http:\/\/www.hsn.com\/products\/seo\/8515581?rdr=1&sourceid=youtube&cm_mmc=Social-_-Youtube-_-ProductVideo-_-577468\r\nHandy Heater 400Watt PlugIn Personal Heater with Remote Control\nPut this pintsized chill chaser to work the next time cold creeps in. The Handy Heater takes up very little space, but delivers...\r\nPrices shown on the previously recorded video may not represent the current price.  View hsn.com to view the current selling price. HSN Item #577468",
    "referenceId": "Tnwkk6GvQJk",
    "date_created": "1507955553",
    "date_modified": "1508372601",
    "tags": "",
    "sourceId": "4",
    "status": "approved",
    "visibility": "1",
    "VV_VI": null,
    "engagement_score": null,
    "conversion_score": null,
    "CVV_VI": null,
    "concept": null,
    "homepage_gallery": null,
    "living": null,
    "id": "123178767",
    "loginId": "1758991",
    "entityType": "1",
    "titleTextEncoded": "Handy-Heater-PlugIn-Personal-Heater-w-Remote-Control",
    "category": "",
    "tvp_profiles": [
        "18"
    ],
    "tvp_profiles_manual": "",
    "tvp_profiles_maxscore": 4034.734,
    "VIDEO_LENGTH": "LONG",
    "duration": 444,
    "settings": "",
    "asset": {
        "type": "youtube",
        "thumbnailUrl": "https:\/\/i.ytimg.com\/vi\/Tnwkk6GvQJk\/sddefault.jpg",
        "uploadDate": 1507955553,
        "videoId": "Tnwkk6GvQJk",
        "title": "Handy Heater PlugIn Personal Heater w\/Remote Control",
        "description": "For More Info or to Buy Now: http:\/\/www.hsn.com\/products\/seo\/8515581?rdr=1&sourceid=youtube&cm_mmc=Social-_-Youtube-_-ProductVideo-_-577468\r\nHandy Heater 400Watt PlugIn Personal Heater with Remote Control\nPut this pintsized chill chaser to work the next time cold creeps in. The Handy Heater takes up very little space, but delivers...\r\nPrices shown on the previously recorded video may not represent the current price.  View hsn.com to view the current selling price. HSN Item #577468",
        "author": "HSNtv",
        "mediaDuration": 444,
        "prettyDuration": "00:07:24",
        "views": "31"
    },
    "transcripts": "",
    "metrics_statistics": "",
    "uploader": ""
}