{
    "title": "[1508436091] Around The World In 78 Days With Mark Beaumont | Ask GCN Anything About Cycling",
    "description": "It's a very special edition of Ask GCN Anything this week, we've got Mark Beaumont, the world record holder for circumnavigating the globe on a bicycle, here to answer all your questions! \n\nSubscribe to GCN: http:\/\/gcn.eu\/SubscribeToGCN\nRegister your interest in the GCN Club: http:\/\/gcn.eu\/qa\nGet exclusive GCN gear in the GCN shop! http:\/\/gcn.eu\/qb\n\nFresh off completing his record breaking ride around the globe, setting a new world record of 78 days 14 hours and 40 minutes in the process, Mark Beaumont is in the GCN studio!!\n\nIn this bumper episode Mark answers all of your questions about his record breaking ride, and they're not all about saddle sores ",
    "referenceId": "zLhWK28usAk",
    "date_created": "1507910412",
    "date_modified": "1508373171",
    "tags": "",
    "sourceId": "4",
    "status": "approved",
    "visibility": "1",
    "VV_VI": null,
    "engagement_score": null,
    "conversion_score": null,
    "CVV_VI": null,
    "concept": null,
    "homepage_gallery": null,
    "living": null,
    "id": "123178848",
    "loginId": "1758991",
    "entityType": "1",
    "titleTextEncoded": "Around-The-World-In-78-Days-With-Mark-Beaumont-Ask-GCN-Anything-About-Cycling",
    "category": "",
    "tvp_profiles": [
        "14",
        "25",
        "32"
    ],
    "tvp_profiles_manual": "",
    "tvp_profiles_maxscore": 5910.617,
    "VIDEO_LENGTH": "LONG",
    "duration": 2144,
    "settings": "",
    "asset": {
        "type": "youtube",
        "thumbnailUrl": "https:\/\/i.ytimg.com\/vi\/zLhWK28usAk\/maxresdefault.jpg",
        "uploadDate": 1507910412,
        "videoId": "zLhWK28usAk",
        "title": "Around The World In 78 Days With Mark Beaumont | Ask GCN Anything About Cycling",
        "description": "It's a very special edition of Ask GCN Anything this week, we've got Mark Beaumont, the world record holder for circumnavigating the globe on a bicycle, here to answer all your questions! \n\nSubscribe to GCN: http:\/\/gcn.eu\/SubscribeToGCN\nRegister your interest in the GCN Club: http:\/\/gcn.eu\/qa\nGet exclusive GCN gear in the GCN shop! http:\/\/gcn.eu\/qb\n\nFresh off completing his record breaking ride around the globe, setting a new world record of 78 days 14 hours and 40 minutes in the process, Mark Beaumont is in the GCN studio!!\n\nIn this bumper episode Mark answers all of your questions about his record breaking ride, and they're not all about saddle sores \ud83d\ude02\n\nLet us know what you think of the legendary Mark Beaumont and his Guinness World Record in the comments below \ud83d\udc47\n\nIf you'd like to contribute captions and video info in your language, here's the link \ud83d\udc4dhttp:\/\/gcn.eu\/qc\n\nWatch more on GCN...\nWatch Si ride with Mark for the first day of his challenge http:\/\/gcn.eu\/atw80Days\ud83d\udcf9 \nAnd then ride part of his final day as well http:\/\/gcn.eu\/78Days \ud83d\udcf9 \n\nPhotos: \u00a9 Bettiniphoto \/ http:\/\/www.bettiniphoto.net\/ & \u00a9Tim De Waele \/ http:\/\/www.tdwsport.com\n\nAbout GCN:\n\nThe Global Cycling Network puts you in the centre of the action: from the iconic climbs of Alpe D\u2019Huez and Mont Ventoux to the cobbles of Flanders, everywhere there is road or pav\u00e9, world-class racing and pro riders, we will be there bringing you action, analysis and unparalleled access every week, every month, and every year. We show you how to be a better cyclist with our bike maintenance videos, tips for improving your cycling, cycling top tens, and not forgetting the weekly GCN Show. Join us on YouTube\u2019s biggest and best cycling channel to get closer to the action and improve your riding!\n\nWelcome to the Global Cycling Network | Inside cycling\n\nThanks to our sponsors:\n\nAlta Badia: http:\/\/gcn.eu\/AltaBadia- \/\/ Maratona Dles Dolomites: http:\/\/gcn.eu\/MaratonaDlesDolomites-\nAssos of Switzerland: http:\/\/gcn.eu\/Assos\nKASK helmets: http:\/\/gcn.eu\/KASK\nfi\u2019zi:k shoes and saddles: http:\/\/gcn.eu\/fizikshoes and http:\/\/gcn.eu\/fiziksaddles\nTopeak tools: http:\/\/gcn.eu\/Topeak\nCanyon bikes: http:\/\/gcn.eu\/-Canyon\nQuarq: http:\/\/gcn.eu\/Quarq\nDT Swiss: http:\/\/gcn.eu\/DtSwiss\nScience in Sport: http:\/\/gcn.eu\/SiS\nOrbea bikes: http:\/\/gcn.eu\/Orbea\nTrek Bicycles: http:\/\/gcn.eu\/-Trek\nVision wheels: http:\/\/gcn.eu\/Vision\nZipp wheels: http:\/\/gcn.eu\/Zipp\npower2max: http:\/\/gcn.eu\/power2max\nWahoo Fitness: http:\/\/gcn.eu\/Wahoo-Fitness \nPark Tool: http:\/\/gcn.eu\/-parktool\nContinental tyres: http:\/\/gcn.eu\/continental-\nCamelbak: http:\/\/gcn.eu\/camelbak-\n\nThe GCN Club - http:\/\/gcn.eu\/club\nYouTube Channel - http:\/\/gcn.eu\/gcnYT\nFacebook - http:\/\/gcn.eu\/gcnFb\nInstagram - http:\/\/gcn.eu\/GCNInsta\nGoogle+ - http:\/\/gcn.eu\/gcnGPlus\nTwitter - http:\/\/gcn.eu\/gcnTW\n\nLeave us a comment below!",
        "author": "Global Cycling Network",
        "mediaDuration": 2144,
        "prettyDuration": "00:35:44",
        "views": "62838"
    },
    "transcripts": "",
    "metrics_statistics": "",
    "uploader": ""
}