{
    "title": "Curtis Stone DuraPan Nonstick 5piece Essentials Cookware Set with Recipes",
    "description": "Curtis Stone Dura-Pan Nonstick 5-piece Essentials Cookware Set with Recipes Cooking is fun with nonstick cookware thats ready to take anything your recipes dish out. Curtis calls this the Essentials set thanks to the versatile sizes and lids; youll call it love when it goes from stovetop to oven to table and looks great doing it. Get everything you need to set up a new kitchen or simply fill out your current collection. Your family will beg you to dish a little more.",
    "referenceId": "Y8omRX1TmU8",
    "date_created": "1507922595",
    "date_modified": "1508372633",
    "tags": "",
    "sourceId": "4",
    "status": "approved",
    "visibility": "1",
    "VV_VI": null,
    "engagement_score": null,
    "conversion_score": null,
    "CVV_VI": null,
    "concept": null,
    "homepage_gallery": null,
    "living": null,
    "id": "123178831",
    "loginId": "1758991",
    "entityType": "1",
    "titleTextEncoded": "Curtis-Stone-DuraPan-Nonstick-5piece-Essentials-Cookware-Set-with-Recipes",
    "category": "",
    "tvp_profiles": [
        "18"
    ],
    "tvp_profiles_manual": "",
    "tvp_profiles_maxscore": 7672.6396,
    "VIDEO_LENGTH": "SHORT",
    "duration": 24,
    "settings": "",
    "asset": {
        "type": "youtube",
        "thumbnailUrl": "https:\/\/i.ytimg.com\/vi\/Y8omRX1TmU8\/maxresdefault.jpg",
        "uploadDate": 1507922595,
        "videoId": "Y8omRX1TmU8",
        "title": "Curtis Stone DuraPan Nonstick 5piece Essentials Cookware Set with Recipes",
        "description": "Curtis Stone Dura-Pan Nonstick 5-piece Essentials Cookware Set with Recipes Cooking is fun with nonstick cookware thats ready to take anything your recipes dish out. Curtis calls this the Essentials set thanks to the versatile sizes and lids; youll call it love when it goes from stovetop to oven to table and looks great doing it. Get everything you need to set up a new kitchen or simply fill out your current collection. Your family will beg you to dish a little more.",
        "author": "HSNtv",
        "mediaDuration": 24,
        "prettyDuration": "00:00:24",
        "views": "5"
    },
    "transcripts": "",
    "metrics_statistics": "",
    "uploader": ""
}