{
    "title": "[1508428454] Gordon's Top Tips for Serving Broccoli - Gordon Ramsay",
    "description": "Gordon Ramsay shows Patsy Kensit his top tips for serving broccoli and plates up his fabulous salmon en croute. From Cookalong Live.",
    "referenceId": "tmo-ag-TcJw",
    "date_created": "1259845553",
    "date_modified": "1508373766",
    "tags": "",
    "sourceId": "4",
    "status": "approved",
    "visibility": "1",
    "VV_VI": null,
    "engagement_score": null,
    "conversion_score": null,
    "CVV_VI": null,
    "concept": null,
    "homepage_gallery": null,
    "living": null,
    "id": "123179504",
    "loginId": "1758991",
    "entityType": "1",
    "titleTextEncoded": "Gordon-s-Top-Tips-for-Serving-Broccoli-Gordon-Ramsay",
    "category": "",
    "tvp_profiles": [
        "18"
    ],
    "tvp_profiles_manual": "",
    "tvp_profiles_maxscore": 8849.477,
    "VIDEO_LENGTH": "SHORT",
    "duration": 149,
    "settings": "",
    "asset": {
        "type": "youtube",
        "thumbnailUrl": "https:\/\/i.ytimg.com\/vi\/tmo-ag-TcJw\/hqdefault.jpg",
        "uploadDate": 1259845553,
        "videoId": "tmo-ag-TcJw",
        "title": "Gordon's Top Tips for Serving Broccoli - Gordon Ramsay",
        "description": "Gordon Ramsay shows Patsy Kensit his top tips for serving broccoli and plates up his fabulous salmon en croute. From Cookalong Live.",
        "author": "Gordon Ramsay",
        "mediaDuration": 149,
        "prettyDuration": "00:02:29",
        "views": "98758"
    },
    "transcripts": "",
    "metrics_statistics": "",
    "uploader": ""
}