{
    "title": "ybf WaterResistant Gel Eyeliners 6piece Set",
    "description": "For More Info or to Buy Now: http:\/\/www.hsn.com\/products\/seo\/8522686?rdr=1&sourceid=youtube&cm_mmc=Social-_-Youtube-_-ProductVideo-_-578723\r\nybf WaterResistant Gel Eyeliners 6piece Set  \n\nWhat It Is \nSet of six eyeliners in everyday, essential colors. Easyon, easyoff waterresistant, retractable liners with built in sharpener. \n\nWhat...\r\nPrices shown on the previously recorded video may not represent the current price.  View hsn.com to view the current selling price. HSN Item #578723",
    "referenceId": "xn8NJ8NOync",
    "date_created": "1508358385",
    "date_modified": "1508372590",
    "tags": "",
    "sourceId": "4",
    "status": "approved",
    "visibility": "1",
    "VV_VI": null,
    "engagement_score": null,
    "conversion_score": null,
    "CVV_VI": null,
    "concept": null,
    "homepage_gallery": null,
    "living": null,
    "id": "123178351",
    "loginId": "1758991",
    "entityType": "1",
    "titleTextEncoded": "ybf-WaterResistant-Gel-Eyeliners-6piece-Set",
    "category": "",
    "tvp_profiles": [
        "9",
        "15"
    ],
    "tvp_profiles_manual": "",
    "tvp_profiles_maxscore": 1998.815,
    "VIDEO_LENGTH": "LONG",
    "duration": 479,
    "settings": "",
    "asset": {
        "type": "youtube",
        "thumbnailUrl": "https:\/\/i.ytimg.com\/vi\/xn8NJ8NOync\/sddefault.jpg",
        "uploadDate": 1508358385,
        "videoId": "xn8NJ8NOync",
        "title": "ybf WaterResistant Gel Eyeliners 6piece Set",
        "description": "For More Info or to Buy Now: http:\/\/www.hsn.com\/products\/seo\/8522686?rdr=1&sourceid=youtube&cm_mmc=Social-_-Youtube-_-ProductVideo-_-578723\r\nybf WaterResistant Gel Eyeliners 6piece Set  \n\nWhat It Is \nSet of six eyeliners in everyday, essential colors. Easyon, easyoff waterresistant, retractable liners with built in sharpener. \n\nWhat...\r\nPrices shown on the previously recorded video may not represent the current price.  View hsn.com to view the current selling price. HSN Item #578723",
        "author": "HSNtv",
        "mediaDuration": 479,
        "prettyDuration": "00:07:59",
        "views": "5"
    },
    "transcripts": "",
    "metrics_statistics": "",
    "uploader": ""
}