{
    "title": "[1508428454] Best Restaurant: Semi-Final 2nd Elimination - Gordon Ramsay",
    "description": "Gordon Ramsay delivers the news that one of the two semi finalists that they are through to the next stage of the competition.\n\nGordon Ramsay in search of Britain's best restaurant. Top restaurants from around the UK compete to win the title.",
    "referenceId": "mzWQSmeD1yU",
    "date_created": "1318342556",
    "date_modified": "1508373263",
    "tags": "",
    "sourceId": "4",
    "status": "approved",
    "visibility": "1",
    "VV_VI": null,
    "engagement_score": null,
    "conversion_score": null,
    "CVV_VI": null,
    "concept": null,
    "homepage_gallery": null,
    "living": null,
    "id": "123179355",
    "loginId": "1758991",
    "entityType": "1",
    "titleTextEncoded": "Best-Restaurant-Semi-Final-2nd-Elimination-Gordon-Ramsay",
    "category": "",
    "tvp_profiles": [
        "18"
    ],
    "tvp_profiles_manual": "",
    "tvp_profiles_maxscore": 2789.3127,
    "VIDEO_LENGTH": "SHORT",
    "duration": 193,
    "settings": "",
    "asset": {
        "type": "youtube",
        "thumbnailUrl": "https:\/\/i.ytimg.com\/vi\/mzWQSmeD1yU\/sddefault.jpg",
        "uploadDate": 1318342556,
        "videoId": "mzWQSmeD1yU",
        "title": "Best Restaurant: Semi-Final 2nd Elimination - Gordon Ramsay",
        "description": "Gordon Ramsay delivers the news that one of the two semi finalists that they are through to the next stage of the competition.\n\nGordon Ramsay in search of Britain's best restaurant. Top restaurants from around the UK compete to win the title.",
        "author": "Gordon Ramsay",
        "mediaDuration": 193,
        "prettyDuration": "00:03:13",
        "views": "4335"
    },
    "transcripts": "",
    "metrics_statistics": "",
    "uploader": ""
}