{
    "title": "[1508440185] Corn Gelatin Shots by Good Food Fast",
    "description": "Try this delicious Candy Corn Gelatin Shots Recipe by Good Food Fast\r\n\r\n\r\nFind the featured items here  https:www.hsn.comshopkitchen-and-foodqc",
    "referenceId": "T8OX_2j9QLg",
    "date_created": "1508179487",
    "date_modified": "1508372595",
    "tags": "",
    "sourceId": "4",
    "status": "approved",
    "visibility": "1",
    "VV_VI": null,
    "engagement_score": null,
    "conversion_score": null,
    "CVV_VI": null,
    "concept": null,
    "homepage_gallery": null,
    "living": null,
    "id": "123178556",
    "loginId": "1758991",
    "entityType": "1",
    "titleTextEncoded": "Corn-Gelatin-Shots-by-Good-Food-Fast",
    "category": "",
    "tvp_profiles": [
        "18",
        "25"
    ],
    "tvp_profiles_manual": "",
    "tvp_profiles_maxscore": 113.68718,
    "VIDEO_LENGTH": "SHORT",
    "duration": 39,
    "settings": "",
    "asset": {
        "type": "youtube",
        "thumbnailUrl": "https:\/\/i.ytimg.com\/vi\/T8OX_2j9QLg\/maxresdefault.jpg",
        "uploadDate": 1508179487,
        "videoId": "T8OX_2j9QLg",
        "title": "Corn Gelatin Shots by Good Food Fast",
        "description": "Try this delicious Candy Corn Gelatin Shots Recipe by Good Food Fast\r\n\r\n\r\nFind the featured items here  https:www.hsn.comshopkitchen-and-foodqc",
        "author": "HSNtv",
        "mediaDuration": 39,
        "prettyDuration": "00:00:39",
        "views": "5"
    },
    "transcripts": "",
    "metrics_statistics": "",
    "uploader": ""
}