{
    "title": "[1508441819] ybf Complexion Perfection with Kabuki Brush",
    "description": "For More Info or to Buy Now: http:\/\/www.hsn.com\/products\/seo\/8123963?rdr=1&sourceid=youtube&cm_mmc=Social-_-Youtube-_-ProductVideo-_-491784\r\nybf Complexion Perfection with Kabuki Brush \nIs perfection impossible to attain? Well, of course it is. Nobody's perfect. But with this unique pinwheel face powder, at least your complexion can...\r\nPrices shown on the previously recorded video may not represent the current price.  View hsn.com to view the current selling price. HSN Item #491784",
    "referenceId": "kU3IjpbaZPk",
    "date_created": "1508369303",
    "date_modified": "1508372590",
    "tags": "",
    "sourceId": "4",
    "status": "approved",
    "visibility": "1",
    "VV_VI": null,
    "engagement_score": null,
    "conversion_score": null,
    "CVV_VI": null,
    "concept": null,
    "homepage_gallery": null,
    "living": null,
    "id": "123178322",
    "loginId": "1758991",
    "entityType": "1",
    "titleTextEncoded": "ybf-Complexion-Perfection-with-Kabuki-Brush",
    "category": "",
    "tvp_profiles": [
        "25"
    ],
    "tvp_profiles_manual": "",
    "tvp_profiles_maxscore": 5841.5728,
    "VIDEO_LENGTH": "LONG",
    "duration": 336,
    "settings": "",
    "asset": {
        "type": "youtube",
        "thumbnailUrl": "https:\/\/i.ytimg.com\/vi\/kU3IjpbaZPk\/sddefault.jpg",
        "uploadDate": 1508369303,
        "videoId": "kU3IjpbaZPk",
        "title": "ybf Complexion Perfection with Kabuki Brush",
        "description": "For More Info or to Buy Now: http:\/\/www.hsn.com\/products\/seo\/8123963?rdr=1&sourceid=youtube&cm_mmc=Social-_-Youtube-_-ProductVideo-_-491784\r\nybf Complexion Perfection with Kabuki Brush \nIs perfection impossible to attain? Well, of course it is. Nobody's perfect. But with this unique pinwheel face powder, at least your complexion can...\r\nPrices shown on the previously recorded video may not represent the current price.  View hsn.com to view the current selling price. HSN Item #491784",
        "author": "HSNtv",
        "mediaDuration": 336,
        "prettyDuration": "00:05:36",
        "views": "2"
    },
    "transcripts": "",
    "metrics_statistics": "",
    "uploader": ""
}