{
    "title": "[1508429236] Gordon Ramsay\u2019s Top 5 Steak Recipes",
    "description": "How to cook the perfect steak in 5 unique ways. Absolutely delicious.\n\nSubscribe for weekly cooking videos. \n\nIf you liked this clip check out the rest of Gordon's channels:\n\nhttp:\/\/www.youtube.com\/gordonramsay\nhttp:\/\/www.youtube.com\/kitchennightmares\nhttp:\/\/www.youtube.com\/thefword",
    "referenceId": "JZVWkjFGCBI",
    "date_created": "1494176403",
    "date_modified": "1508373254",
    "tags": "",
    "sourceId": "4",
    "status": "approved",
    "visibility": "1",
    "VV_VI": null,
    "engagement_score": null,
    "conversion_score": null,
    "CVV_VI": null,
    "concept": null,
    "homepage_gallery": null,
    "living": null,
    "id": "123178979",
    "loginId": "1758991",
    "entityType": "1",
    "titleTextEncoded": "Gordon-Ramsay-s-Top-5-Steak-Recipes",
    "category": "",
    "tvp_profiles": [
        "18",
        "11",
        "32"
    ],
    "tvp_profiles_manual": "",
    "tvp_profiles_maxscore": 501.61737,
    "VIDEO_LENGTH": "LONG",
    "duration": 1002,
    "settings": "",
    "asset": {
        "type": "youtube",
        "thumbnailUrl": "https:\/\/i.ytimg.com\/vi\/JZVWkjFGCBI\/maxresdefault.jpg",
        "uploadDate": 1494176403,
        "videoId": "JZVWkjFGCBI",
        "title": "Gordon Ramsay\u2019s Top 5 Steak Recipes",
        "description": "How to cook the perfect steak in 5 unique ways. Absolutely delicious.\n\nSubscribe for weekly cooking videos. \n\nIf you liked this clip check out the rest of Gordon's channels:\n\nhttp:\/\/www.youtube.com\/gordonramsay\nhttp:\/\/www.youtube.com\/kitchennightmares\nhttp:\/\/www.youtube.com\/thefword",
        "author": "Gordon Ramsay",
        "mediaDuration": 1002,
        "prettyDuration": "00:16:42",
        "views": "3595828"
    },
    "transcripts": "",
    "metrics_statistics": "",
    "uploader": ""
}