{
    "title": "[1508436091] HSN Summer Host Pick",
    "description": "Cheers to 40 years!  Our best one yet!   Shop now at https:\/\/www.hsn.com\/",
    "referenceId": "fFWkv8sd--o",
    "date_created": "1498130901",
    "date_modified": "1508372439",
    "tags": "",
    "sourceId": "4",
    "status": "approved",
    "visibility": "1",
    "VV_VI": null,
    "engagement_score": null,
    "conversion_score": null,
    "CVV_VI": null,
    "concept": null,
    "homepage_gallery": null,
    "living": null,
    "id": "123178240",
    "loginId": "1758991",
    "entityType": "1",
    "titleTextEncoded": "HSN-Summer-Host-Pick",
    "category": "",
    "tvp_profiles": [
        "18"
    ],
    "tvp_profiles_manual": "",
    "tvp_profiles_maxscore": 159.72328,
    "VIDEO_LENGTH": "SHORT",
    "duration": 31,
    "settings": "",
    "asset": {
        "type": "youtube",
        "thumbnailUrl": "https:\/\/i.ytimg.com\/vi\/fFWkv8sd--o\/maxresdefault.jpg",
        "uploadDate": 1498130901,
        "videoId": "fFWkv8sd--o",
        "title": "HSN Summer Host Pick",
        "description": "Cheers to 40 years!  Our best one yet!   Shop now at https:\/\/www.hsn.com\/",
        "author": "HSN",
        "mediaDuration": 31,
        "prettyDuration": "00:00:31",
        "views": "529"
    },
    "transcripts": "",
    "metrics_statistics": "",
    "uploader": ""
}